{
  "version": "1757103264976",
  "timestamp": "2024-01-07T14:54:24.976Z",
  "files": {
    "Main.js": "1757103264976",
    "handlers.js": "1757103264976", 
    "ui.js": "1757103264976",
    "services.js": "1757103264976",
    "utils.js": "1757103264976",
    "Map.js": "1757103264976",
    "Gemini.js": "1757103264976",
    "version.js": "1757103264976",
    "style.css": "1757103264976",
    "index.html": "1757103264976"
  },
  "mobile_fix": {
    "applied": true,
    "method": "merged-into-main-css",
    "priority": "critical",
    "status": "production-ready"
  },
  "qa_status": {
    "comprehensive_review": "completed",
    "critical_issues_fixed": true,
    "production_ready": true,
    "last_review": "2024-01-07T14:54:24.976Z",
    "deployment_status": "ready"
  }
}
